mattermostwrapper/__init__.py
mattermostwrapper/wrapper.py
mattermostwrapper-2.1.dist-info/DESCRIPTION.rst
mattermostwrapper-2.1.dist-info/METADATA
mattermostwrapper-2.1.dist-info/RECORD
mattermostwrapper-2.1.dist-info/WHEEL
mattermostwrapper-2.1.dist-info/metadata.json
mattermostwrapper-2.1.dist-info/top_level.txt
wrapper/__init__.py
wrapper/wrapper.py
