Metadata-Version: 1.1
Name: mattermostwrapper
Version: 2.1
Summary: A mattermost api v4 wrapper to interact with api
Home-page: https://github.com/btotharye/mattermostwrapper.git
Author: Brian Hopkins
Author-email: btotharye@gmail.com
License: MIT
Download-URL: https://github.com/btotharye/mattermostwrapper/archive/2.0.tar.gz
Platform: UNKNOWN
